self_destruct/__init__.py
self_destruct/__main__.py
self_destruct/explosives.py
self_destruct-0.1.0.dist-info/licenses/LICENSE
self_destruct-0.1.0.dist-info/METADATA
self_destruct-0.1.0.dist-info/WHEEL
self_destruct-0.1.0.dist-info/top_level.txt
self_destruct-0.1.0.dist-info/RECORD
