Metadata-Version: 2.4
Name: self-destruct
Version: 0.1.0
Summary: A simple way for EC2 instances to stop/terminate themselves.
Author-email: Tom Morrell <Thomas.Albert.Morrell@gmail.com>
Project-URL: Homepage, https://github.com/TomMorrell/self-destruct
Project-URL: Issues, https://github.com/TomMorrell/self-destruct/issues
Keywords: AWS,EC2,terminate
Classifier: Intended Audience :: Developers
Classifier: License :: OSI Approved :: MIT License
Classifier: Natural Language :: English
Classifier: Operating System :: OS Independent
Classifier: Programming Language :: Python :: 3
Requires-Python: >=3.9
License-File: LICENSE
Requires-Dist: boto3
Requires-Dist: ec2-metadata
Dynamic: license-file
